<greyButton>
	
	<!-- Parametres du template -->
	<Param name="width" >100</Param>
	<Param name="height" >30</Param>
	<Param name="label">Text</Param>
	<Param name="name" />
	<Param name="Anchors" />
	<Param name="Hooks"><onRelease /></Param>
	<Param name="css" >[config.ui.skin]css/button.css</Param>
	<Param name="cssClass" >center</Param>
	
	<!-- Variables internes au template -->
	<Var name="labelWidth">#width - 4</Var>	
	<Var name="textureName">'btn_texture_' + '#name'</Var>
	<Var name="labelName">'btn_lbl_' + '#name'</Var>
	
	<Button name="#name">
		<Common>
			<Anchors>#Anchors</Anchors>
			<Texture strata="LOW" name="$textureName">
				<Size>
					<AbsDimension x="#width" y="#height" />
				</Size>
				<gotoAndStop>normal</gotoAndStop>
				<autoGrid>true</autoGrid>
				<uri>[local.assets]btn_beige</uri>
			</Texture>
			
			<Label name="$labelName">
				<Size>
					<AbsDimension x="$labelWidth" y="#height" />
				</Size>
				<text>#label</text>
				<cssClass>#cssClass</cssClass>
				<css>#css</css>
				<verticalAlign>center</verticalAlign>
			</Label>
			
			<Hooks>#Hooks</Hooks>
		</Common>
		
		<State type="OVER">
			<SetProperties target="$textureName">
				<gotoAndStop>over</gotoAndStop>
			</SetProperties>
		</State>
		
		<State type="PRESSED">
			<SetProperties target="$textureName">
				<gotoAndStop>pressed</gotoAndStop>
			</SetProperties>
		</State>
	</Button>
	
</greyButton>